[
  {
    "id": "ajax-zwolle",
    "league": "Eredivisie",
    "team1": {
      "name": "Ajax",
      "logo": "https://static.flashscore.com/res/image/data/hEQxyYA6-bZZPiwAI.png"
    },
    "team2": {
      "name": "Zwolle",
      "logo": "https://static.flashscore.com/res/image/data/jDtO0Y5k-vFbzuVd5.png"
    },
    "kickoff_date": "2025-09-13",
    "kickoff_time": "21:30",
    "match_date": "2025-09-13",
    "match_time": "21:20",
    "duration": "3.5",
    "icon": "https://via.placeholder.com/30.png?text=Soccer",
    "servers": [],
    "is_womens": false
  },
  {
    "id": "gaeagles-fcvolendam",
    "league": "Eredivisie",
    "team1": {
      "name": "G.A. Eagles",
      "logo": "https://static.flashscore.com/res/image/data/4IPDw4ne-x4Xh4Pu0.png"
    },
    "team2": {
      "name": "FC Volendam",
      "logo": "https://static.flashscore.com/res/image/data/8tDUPO86-WYtEUtB2.png"
    },
    "kickoff_date": "2025-09-13",
    "kickoff_time": "23:45",
    "match_date": "2025-09-13",
    "match_time": "23:35",
    "duration": "3.5",
    "icon": "https://via.placeholder.com/30.png?text=Soccer",
    "servers": [],
    "is_womens": false
  },
  {
    "id": "nijmegen-psv",
    "league": "Eredivisie",
    "team1": {
      "name": "Nijmegen",
      "logo": "https://static.flashscore.com/res/image/data/C8FCtESq-4vob7cTR.png"
    },
    "team2": {
      "name": "PSV",
      "logo": "https://static.flashscore.com/res/image/data/fefX7RQq-j5zA1baQ.png"
    },
    "kickoff_date": "2025-09-13",
    "kickoff_time": "23:45",
    "match_date": "2025-09-13",
    "match_time": "23:35",
    "duration": "3.5",
    "icon": "https://via.placeholder.com/30.png?text=Soccer",
    "servers": [],
    "is_womens": false
  },
  {
    "id": "arsenal-nottingham",
    "league": "Premier League",
    "team1": {
      "name": "Arsenal",
      "logo": "https://static.flashscore.com/res/image/data/0n1ffK6k-vcNAdtF9.png"
    },
    "team2": {
      "name": "Nottingham",
      "logo": "https://static.flashscore.com/res/image/data/86ODdyle-ImKwLTtA.png"
    },
    "kickoff_date": "2025-09-13",
    "kickoff_time": "18:30",
    "match_date": "2025-09-13",
    "match_time": "18:20",
    "duration": "3.5",
    "icon": "https://via.placeholder.com/30.png?text=Soccer",
    "servers": [],
    "is_womens": false
  },
  {
    "id": "bournemouth-brighton",
    "league": "Premier League",
    "team1": {
      "name": "Bournemouth",
      "logo": "https://static.flashscore.com/res/image/data/C60HMWTH-tCGtX12c.png"
    },
    "team2": {
      "name": "Brighton",
      "logo": "https://static.flashscore.com/res/image/data/G0q9xjRq-b92lfEJC.png"
    },
    "kickoff_date": "2025-09-13",
    "kickoff_time": "21:00",
    "match_date": "2025-09-13",
    "match_time": "20:50",
    "duration": "3.5",
    "icon": "https://via.placeholder.com/30.png?text=Soccer",
    "servers": [],
    "is_womens": false
  },
  {
    "id": "crystalpalace-sunderland",
    "league": "Premier League",
    "team1": {
      "name": "Crystal Palace",
      "logo": "https://static.flashscore.com/res/image/data/GfkvlLmC-pzMOQXRe.png"
    },
    "team2": {
      "name": "Sunderland",
      "logo": "https://static.flashscore.com/res/image/data/rPPdotBN-0d34NJCO.png"
    },
    "kickoff_date": "2025-09-13",
    "kickoff_time": "21:00",
    "match_date": "2025-09-13",
    "match_time": "20:50",
    "duration": "3.5",
    "icon": "https://via.placeholder.com/30.png?text=Soccer",
    "servers": [],
    "is_womens": false
  },
  {
    "id": "everton-astonvilla",
    "league": "Premier League",
    "team1": {
      "name": "Everton",
      "logo": "https://static.flashscore.com/res/image/data/EBfZuwme-bRmKmISE.png"
    },
    "team2": {
      "name": "Aston Villa",
      "logo": "https://static.flashscore.com/res/image/data/UHchCEVH-jwz95gs0.png"
    },
    "kickoff_date": "2025-09-13",
    "kickoff_time": "21:00",
    "match_date": "2025-09-13",
    "match_time": "20:50",
    "duration": "3.5",
    "icon": "https://via.placeholder.com/30.png?text=Soccer",
    "servers": [],
    "is_womens": false
  },
  {
    "id": "fulham-leeds",
    "league": "Premier League",
    "team1": {
      "name": "Fulham",
      "logo": "https://static.flashscore.com/res/image/data/fkbYUWme-ImMEe0UF.png"
    },
    "team2": {
      "name": "Leeds",
      "logo": "https://static.flashscore.com/res/image/data/lvs4WW5k-O4P6Zhap.png"
    },
    "kickoff_date": "2025-09-13",
    "kickoff_time": "21:00",
    "match_date": "2025-09-13",
    "match_time": "20:50",
    "duration": "3.5",
    "icon": "https://via.placeholder.com/30.png?text=Soccer",
    "servers": [],
    "is_womens": false
  },
  {
    "id": "newcastle-wolves",
    "league": "Premier League",
    "team1": {
      "name": "Newcastle",
      "logo": "https://static.flashscore.com/res/image/data/UXo7VXPq-ImMEe0UF.png"
    },
    "team2": {
      "name": "Wolves",
      "logo": "https://static.flashscore.com/res/image/data/OMUzjDkC-CjV6Eptm.png"
    },
    "kickoff_date": "2025-09-13",
    "kickoff_time": "21:00",
    "match_date": "2025-09-13",
    "match_time": "20:50",
    "duration": "3.5",
    "icon": "https://via.placeholder.com/30.png?text=Soccer",
    "servers": [],
    "is_womens": false
  },
  {
    "id": "westham-tottenham",
    "league": "Premier League",
    "team1": {
      "name": "West Ham",
      "logo": "https://static.flashscore.com/res/image/data/YeSfKGlC-Q9DJHs4l.png"
    },
    "team2": {
      "name": "Tottenham",
      "logo": "https://static.flashscore.com/res/image/data/v3SzDxVH-Ig5FKJZ5.png"
    },
    "kickoff_date": "2025-09-13",
    "kickoff_time": "23:30",
    "match_date": "2025-09-13",
    "match_time": "23:20",
    "duration": "3.5",
    "icon": "https://via.placeholder.com/30.png?text=Soccer",
    "servers": [],
    "is_womens": false
  },
  {
    "id": "marseille-lorient",
    "league": "Ligue 1",
    "team1": {
      "name": "Marseille",
      "logo": "https://static.flashscore.com/res/image/data/t6Kb5X76-voNnDKJK.png"
    },
    "team2": {
      "name": "Lorient",
      "logo": "https://static.flashscore.com/res/image/data/0r9EzUS0-GU4hlIMk.png"
    },
    "kickoff_date": "2025-09-13",
    "kickoff_time": "01:45",
    "match_date": "2025-09-13",
    "match_time": "01:35",
    "duration": "3.5",
    "icon": "https://via.placeholder.com/30.png?text=Soccer",
    "servers": [],
    "is_womens": false
  },
  {
    "id": "nice-nantes",
    "league": "Ligue 1",
    "team1": {
      "name": "Nice",
      "logo": "https://static.flashscore.com/res/image/data/bJCGymle-00sqJmg8.png"
    },
    "team2": {
      "name": "Nantes",
      "logo": "https://static.flashscore.com/res/image/data/vTVURLne-YBWLmubi.png"
    },
    "kickoff_date": "2025-09-13",
    "kickoff_time": "22:00",
    "match_date": "2025-09-13",
    "match_time": "21:50",
    "duration": "3.5",
    "icon": "https://via.placeholder.com/30.png?text=Soccer",
    "servers": [],
    "is_womens": false
  },
  {
    "id": "bayerleverkusen-eintrachtfrankfurt",
    "league": "Bundesliga",
    "team1": {
      "name": "Bayer Leverkusen",
      "logo": "https://static.flashscore.com/res/image/data/dWZYQIPq-WrjrBuU2.png"
    },
    "team2": {
      "name": "Eintracht Frankfurt",
      "logo": "https://static.flashscore.com/res/image/data/2aegVtQq-86lnAaq9.png"
    },
    "kickoff_date": "2025-09-13",
    "kickoff_time": "01:30",
    "match_date": "2025-09-13",
    "match_time": "01:20",
    "duration": "3.5",
    "icon": "https://via.placeholder.com/30.png?text=Soccer",
    "servers": [],
    "is_womens": false
  },
  {
    "id": "freiburg-stuttgart",
    "league": "Bundesliga",
    "team1": {
      "name": "Freiburg",
      "logo": "https://static.flashscore.com/res/image/data/0pdxCFiT-86lnAaq9.png"
    },
    "team2": {
      "name": "Stuttgart",
      "logo": "https://static.flashscore.com/res/image/data/fgQWGn86-f1Z3XxZa.png"
    },
    "kickoff_date": "2025-09-13",
    "kickoff_time": "20:30",
    "match_date": "2025-09-13",
    "match_time": "20:20",
    "duration": "3.5",
    "icon": "https://via.placeholder.com/30.png?text=Soccer",
    "servers": [],
    "is_womens": false
  },
  {
    "id": "heidenheim-dortmund",
    "league": "Bundesliga",
    "team1": {
      "name": "Heidenheim",
      "logo": "https://static.flashscore.com/res/image/data/UH4XQKBN-ncNaLxYl.png"
    },
    "team2": {
      "name": "Dortmund",
      "logo": "https://static.flashscore.com/res/image/data/xSfDCO76-WrjrBuU2.png"
    },
    "kickoff_date": "2025-09-13",
    "kickoff_time": "20:30",
    "match_date": "2025-09-13",
    "match_time": "20:20",
    "duration": "3.5",
    "icon": "https://via.placeholder.com/30.png?text=Soccer",
    "servers": [],
    "is_womens": false
  },
  {
    "id": "mainz-rbleipzig",
    "league": "Bundesliga",
    "team1": {
      "name": "Mainz",
      "logo": "https://static.flashscore.com/res/image/data/tbR3gUTH-bsE5kOg9.png"
    },
    "team2": {
      "name": "RB Leipzig",
      "logo": "https://static.flashscore.com/res/image/data/fNS5fTmC-WvvSE8Dm.png"
    },
    "kickoff_date": "2025-09-13",
    "kickoff_time": "20:30",
    "match_date": "2025-09-13",
    "match_time": "20:20",
    "duration": "3.5",
    "icon": "https://via.placeholder.com/30.png?text=Soccer",
    "servers": [],
    "is_womens": false
  },
  {
    "id": "unionberlin-hoffenheim",
    "league": "Bundesliga",
    "team1": {
      "name": "Union Berlin",
      "logo": "https://static.flashscore.com/res/image/data/0OMJUule-ncmj9JbF.png"
    },
    "team2": {
      "name": "Hoffenheim",
      "logo": "https://static.flashscore.com/res/image/data/IyZBMF7k-n7lWn9DL.png"
    },
    "kickoff_date": "2025-09-13",
    "kickoff_time": "20:30",
    "match_date": "2025-09-13",
    "match_time": "20:20",
    "duration": "3.5",
    "icon": "https://via.placeholder.com/30.png?text=Soccer",
    "servers": [],
    "is_womens": false
  },
  {
    "id": "wolfsburg-fckoln",
    "league": "Bundesliga",
    "team1": {
      "name": "Wolfsburg",
      "logo": "https://static.flashscore.com/res/image/data/2cDrWAS0-KjF1j4v3.png"
    },
    "team2": {
      "name": "FC Koln",
      "logo": "https://static.flashscore.com/res/image/data/KMphsCCN-86lnAaq9.png"
    },
    "kickoff_date": "2025-09-13",
    "kickoff_time": "20:30",
    "match_date": "2025-09-13",
    "match_time": "20:20",
    "duration": "3.5",
    "icon": "https://via.placeholder.com/30.png?text=Soccer",
    "servers": [],
    "is_womens": false
  },
  {
    "id": "bayernmunich-hamburgersv",
    "league": "Bundesliga",
    "team1": {
      "name": "Bayern Munich",
      "logo": "https://static.flashscore.com/res/image/data/lWGBVoA6-SvLFaVNH.png"
    },
    "team2": {
      "name": "Hamburger SV",
      "logo": "https://static.flashscore.com/res/image/data/dWB5gKjC-86lnAaq9.png"
    },
    "kickoff_date": "2025-09-13",
    "kickoff_time": "23:30",
    "match_date": "2025-09-13",
    "match_time": "23:20",
    "duration": "3.5",
    "icon": "https://via.placeholder.com/30.png?text=Soccer",
    "servers": [],
    "is_womens": false
  },
  {
    "id": "cagliari-parma",
    "league": "Serie A",
    "team1": {
      "name": "Cagliari",
      "logo": "https://static.flashscore.com/res/image/data/tSQII3hT-McvX4bye.png"
    },
    "team2": {
      "name": "Parma",
      "logo": "https://static.flashscore.com/res/image/data/WI9nVggT-fydXzLY6.png"
    },
    "kickoff_date": "2025-09-13",
    "kickoff_time": "20:00",
    "match_date": "2025-09-13",
    "match_time": "19:50",
    "duration": "3.5",
    "icon": "https://via.placeholder.com/30.png?text=Soccer",
    "servers": [],
    "is_womens": false
  },
  {
    "id": "juventus-inter",
    "league": "Serie A",
    "team1": {
      "name": "Juventus",
      "logo": "https://static.flashscore.com/res/image/data/xxLGMOlC-EXzXDYgS.png"
    },
    "team2": {
      "name": "Inter",
      "logo": "https://static.flashscore.com/res/image/data/fLNbBiQq-jDrBQiMS.png"
    },
    "kickoff_date": "2025-09-13",
    "kickoff_time": "23:00",
    "match_date": "2025-09-13",
    "match_time": "22:50",
    "duration": "3.5",
    "icon": "https://via.placeholder.com/30.png?text=Soccer",
    "servers": [],
    "is_womens": false
  },
  {
    "id": "sevilla-elche",
    "league": "LaLiga",
    "team1": {
      "name": "Sevilla",
      "logo": "https://static.flashscore.com/res/image/data/EcTGi086-tIT0KyhE.png"
    },
    "team2": {
      "name": "Elche",
      "logo": "https://static.flashscore.com/res/image/data/EVxB82BN-YmCZKGcR.png"
    },
    "kickoff_date": "2025-09-13",
    "kickoff_time": "02:00",
    "match_date": "2025-09-13",
    "match_time": "01:50",
    "duration": "3.5",
    "icon": "https://via.placeholder.com/30.png?text=Soccer",
    "servers": [],
    "is_womens": false
  },
  {
    "id": "getafe-roviedo",
    "league": "LaLiga",
    "team1": {
      "name": "Getafe",
      "logo": "https://static.flashscore.com/res/image/data/hGMWMdT0-YmCZKGcR.png"
    },
    "team2": {
      "name": "R. Oviedo",
      "logo": "https://static.flashscore.com/res/image/data/8CuFFxlC-Y7pkY0PJ.png"
    },
    "kickoff_date": "2025-09-13",
    "kickoff_time": "19:00",
    "match_date": "2025-09-13",
    "match_time": "18:50",
    "duration": "3.5",
    "icon": "https://via.placeholder.com/30.png?text=Soccer",
    "servers": [],
    "is_womens": false
  },
  {
    "id": "realsociedad-realmadrid",
    "league": "LaLiga",
    "team1": {
      "name": "Real Sociedad",
      "logo": "https://static.flashscore.com/res/image/data/rcAkl5le-vJb36ZBF.png"
    },
    "team2": {
      "name": "Real Madrid",
      "logo": "https://static.flashscore.com/res/image/data/CGPhnpne-fcDVLdrL.png"
    },
    "kickoff_date": "2025-09-13",
    "kickoff_time": "21:15",
    "match_date": "2025-09-13",
    "match_time": "21:05",
    "duration": "3.5",
    "icon": "https://via.placeholder.com/30.png?text=Soccer",
    "servers": [],
    "is_womens": false
  },
  {
    "id": "athbilbao-alaves",
    "league": "LaLiga",
    "team1": {
      "name": "Ath Bilbao",
      "logo": "https://static.flashscore.com/res/image/data/GUtNYAWH-vJb36ZBF.png"
    },
    "team2": {
      "name": "Alaves",
      "logo": "https://static.flashscore.com/res/image/data/4rBxR4R0-4U3vjZKk.png"
    },
    "kickoff_date": "2025-09-13",
    "kickoff_time": "23:30",
    "match_date": "2025-09-13",
    "match_time": "23:20",
    "duration": "3.5",
    "icon": "https://via.placeholder.com/30.png?text=Soccer",
    "servers": [],
    "is_womens": false
  },
  {
    "id": "Bulgaria-Spain",
    "league": "World Championship - Qualification",
    "team1": {
      "name": "Bulgaria",
      "logo": "https://static.flashscore.com/res/image/data/6VTk1W9r-Iyld3bDd.png"
    },
    "team2": {
      "name": "Spain",
      "logo": "https://static.flashscore.com/res/image/data/Od7JGXZA-0E8Iihe1.png"
    },
    "kickoff_date": "2025-09-05",
    "kickoff_time": "01:45",
    "match_date": "2025-09-05",
    "match_time": "01:45",
    "duration": "3.5",
    "icon": "https://via.placeholder.com/30.png?text=Soccer",
    "servers": [
      {
        "url": "https://listcanal.blogspot.com/?id=SPORT1CZ",
        "label": "CH-CZ"
      },
      {
        "url": "https://hls.govoet.my.id/?id=BEIN1",
        "label": "CH-AR"
      },
      {
        "url": "https://multi.govoet.my.id/?ss=hd1",
        "label": "CH-EN"
      },
      {
        "url": "https://multi.govoet.my.id/?ss=hd6",
        "label": "CH-ES"
      },
      {
        "url": "https://multi.govoet.my.id/?ss=sporttv1",
        "label": "CH-PT"
      },
      {
        "url": "https://multi.govoet.my.id/?ss=br1",
        "label": "CH-ES"
      }
    ],
    "is_womens": false
  },
  {
    "id": "Liechtenstein-Belgium",
    "league": "World Championship - Qualification",
    "team1": {
      "name": "Liechtenstein",
      "logo": "https://static.flashscore.com/res/image/data/xQpISrDr-08oJ2RMo.png"
    },
    "team2": {
      "name": "Belgium",
      "logo": "https://static.flashscore.com/res/image/data/Qur1J5jl-dtrVaP64.png"
    },
    "kickoff_date": "2025-09-05",
    "kickoff_time": "01:45",
    "match_date": "2025-09-05",
    "match_time": "01:45",
    "duration": "3.5",
    "icon": "https://via.placeholder.com/30.png?text=Soccer",
    "servers": [
      {
        "url": "https://multi.govoet.my.id/?ss=hd11",
        "label": "CH-EN"
      },
      {
        "url": "https://multi.govoet.my.id/?ss=sporttv4",
        "label": "CH-PT"
      }
    ],
    "is_womens": false
  },
  {
    "id": "Luxembourg-Northern-Ireland",
    "league": "World Championship - Qualification",
    "team1": {
      "name": "Luxembourg",
      "logo": "https://static.flashscore.com/res/image/data/6Ja9JTjl-jovscNjN.png"
    },
    "team2": {
      "name": "Northern Ireland",
      "logo": "https://static.flashscore.com/res/image/data/MBTTYzDa-fazrR153.png"
    },
    "kickoff_date": "2025-09-05",
    "kickoff_time": "01:45",
    "match_date": "2025-09-05",
    "match_time": "01:45",
    "duration": "3.5",
    "icon": "https://via.placeholder.com/30.png?text=Soccer",
    "servers": [
      {
        "url": "https://multi.govoet.my.id/?ss=hd2",
        "label": "CH-EN"
      }
    ],
    "is_womens": false
  },
  {
    "id": "Netherlands-Poland",
    "league": "World Championship - Qualification",
    "team1": {
      "name": "Netherlands",
      "logo": "https://static.flashscore.com/res/image/data/bieizLjl-fazrR153.png"
    },
    "team2": {
      "name": "Poland",
      "logo": "https://static.flashscore.com/res/image/data/zB15YqDr-vZG58BBc.png"
    },
    "kickoff_date": "2025-09-05",
    "kickoff_time": "01:45",
    "match_date": "2025-09-05",
    "match_time": "01:45",
    "duration": "3.5",
    "icon": "https://via.placeholder.com/30.png?text=Soccer",
    "servers": [
      {
        "url": "https://listcanal.blogspot.com/?id=SPORT2CZ",
        "label": "CH-CZ"
      },
      {
        "url": "https://multi.govoet.my.id/?shaka=arena1p",
        "label": "CH-HR"
      },
      {
        "url": "https://multi.govoet.my.id/?iframe=aHR0cHM6Ly9iaWtpbmJhcnU5Ni5ibG9nc3BvdC5jb20vcC9wbGF5ZXJtcGQuaHRtbD9jaGFubmVsPXNvY2NlcmNoYW5uZWw=",
        "label": "CH-EN"
      },
      {
        "url": "https://multi.govoet.my.id/?ss=hd9",
        "label": "CH-EN"
      },
      {
        "url": "https://multi.govoet.my.id/?ss=hd4",
        "label": "CH-NL"
      },
      {
        "url": "https://multi.govoet.my.id/?ss=sporttv2",
        "label": "CH-PT"
      },
      {
        "url": "https://multi.govoet.my.id/?ss=br2",
        "label": "CH-ES"
      }
    ],
    "is_womens": false
  },
  {
    "id": "Slovakia-Germany",
    "league": "World Championship - Qualification",
    "team1": {
      "name": "Slovakia",
      "logo": "https://static.flashscore.com/res/image/data/phJfHhHG-byN2hxSj.png"
    },
    "team2": {
      "name": "Germany",
      "logo": "https://static.flashscore.com/res/image/data/zP226aXg-fB4vYUZp.png"
    },
    "kickoff_date": "2025-09-05",
    "kickoff_time": "01:45",
    "match_date": "2025-09-05",
    "match_time": "01:45",
    "duration": "3.5",
    "icon": "https://via.placeholder.com/30.png?text=Soccer",
    "servers": [
      {
        "url": "https://multi.govoet.my.id/?shaka=arena2p",
        "label": "CH-HR"
      },
      {
        "url": "https://multi.govoet.my.id/?ss=hd3",
        "label": "CH-GR"
      },
      {
        "url": "https://multi.govoet.my.id/?ss=sporttv3",
        "label": "CH-PT"
      }
    ],
    "is_womens": false
  },
  {
    "id": "Argentina-Venezuela",
    "league": "World Championship - Qualification - Round 17",
    "team1": {
      "name": "Argentina",
      "logo": "https://static.flashscore.com/res/image/data/xQCUe9zB-AmY8ktbk.png"
    },
    "team2": {
      "name": "Venezuela",
      "logo": "https://static.flashscore.com/res/image/data/Knqi3yxS-jclZerLL.png"
    },
    "kickoff_date": "2025-09-05",
    "kickoff_time": "06:30",
    "match_date": "2025-09-05",
    "match_time": "06:30",
    "duration": "3.5",
    "icon": "https://via.placeholder.com/30.png?text=Soccer",
    "servers": [
      {
        "url": "https://multi.govoet.my.id/?shaka=universo",
        "label": "CH-ES"
      },
      {
        "url": "https://multi.govoet.my.id/?shaka=arena1p",
        "label": "CH-HR"
      },
      {
        "url": "https://multi.govoet.my.id/?shaka=espn2nl",
        "label": "CH-NL"
      },
      {
        "url": "https://multi.govoet.my.id/?shaka=espn1nl",
        "label": "CH-NL"
      },
      {
        "url": "https://multi.govoet.my.id/?ss=hd2",
        "label": "CH-EN"
      },
      {
        "url": "https://multi.govoet.my.id/?ss=hd6",
        "label": "CH-ES"
      },
      {
        "url": "https://multi.govoet.my.id/?ss=sporttv2",
        "label": "CH-PT"
      }
    ],
    "is_womens": false
  },
  {
    "id": "Colombia-Bolivia",
    "league": "World Championship - Qualification - Round 17",
    "team1": {
      "name": "Colombia",
      "logo": "https://static.flashscore.com/res/image/data/Ymt6NG9r-C6kVdO5F.png"
    },
    "team2": {
      "name": "Bolivia",
      "logo": "https://static.flashscore.com/res/image/data/voJCcZf5-Ik5Zg8Xj.png"
    },
    "kickoff_date": "2025-09-05",
    "kickoff_time": "06:30",
    "match_date": "2025-09-05",
    "match_time": "06:30",
    "duration": "3.5",
    "icon": "https://via.placeholder.com/30.png?text=Soccer",
    "servers": [
      {
        "url": "https://multi.govoet.my.id/?ss=hd8",
        "label": "CH-ES"
      }
    ],
    "is_womens": false
  },
  {
    "id": "Paraguay-Ecuador",
    "league": "World Championship - Qualification - Round 17",
    "team1": {
      "name": "Paraguay",
      "logo": "https://static.flashscore.com/res/image/data/xlHCGmwS-I5qbBI7s.png"
    },
    "team2": {
      "name": "Ecuador",
      "logo": "https://static.flashscore.com/res/image/data/Qkovv0wS-IPF97VQ3.png"
    },
    "kickoff_date": "2025-09-05",
    "kickoff_time": "06:30",
    "match_date": "2025-09-05",
    "match_time": "06:30",
    "duration": "3.5",
    "icon": "https://via.placeholder.com/30.png?text=Soccer",
    "servers": [
      {
        "url": "https://multi.govoet.my.id/?ss=hd10",
        "label": "CH-EN"
      }
    ],
    "is_womens": false
  },
  {
    "id": "Uruguay-Peru",
    "league": "World Championship - Qualification - Round 17",
    "team1": {
      "name": "Uruguay",
      "logo": "https://static.flashscore.com/res/image/data/ddzsJgf5-WdZ4jMrq.png"
    },
    "team2": {
      "name": "Peru",
      "logo": "https://static.flashscore.com/res/image/data/nk3TfRGG-6aZroxFP.png"
    },
    "kickoff_date": "2025-09-05",
    "kickoff_time": "06:30",
    "match_date": "2025-09-05",
    "match_time": "06:30",
    "duration": "3.5",
    "icon": "https://via.placeholder.com/30.png?text=Soccer",
    "servers": [
      {
        "url": "https://multi.govoet.my.id/?ss=hd11",
        "label": "CH-EN"
      }
    ],
    "is_womens": false
  },
  {
    "id": "Brazil-Chile",
    "league": "World Championship - Qualification - Round 17",
    "team1": {
      "name": "Brazil",
      "logo": "https://static.flashscore.com/res/image/data/hCaVxehl-88LAtdNt.png"
    },
    "team2": {
      "name": "Chile",
      "logo": "https://static.flashscore.com/res/image/data/z3ijbXdM-dYPS3tqD.png"
    },
    "kickoff_date": "2025-09-05",
    "kickoff_time": "07:30",
    "match_date": "2025-09-05",
    "match_time": "07:30",
    "duration": "3.5",
    "icon": "https://via.placeholder.com/30.png?text=Soccer",
    "servers": [
      {
        "url": "https://multi.govoet.my.id/?jw=universo",
        "label": "CH-ES"
      },
      {
        "url": "https://multi.govoet.my.id/?jw=sscnews",
        "label": "CH-AR"
      },
      {
        "url": "https://multi.govoet.my.id/?iframe=aHR0cHM6Ly9iaWtpbmJhcnU5Ni5ibG9nc3BvdC5jb20vcC9wbGF5ZXJtcGQuaHRtbD9jaGFubmVsPXNvY2NlcmNoYW5uZWw=",
        "label": "CH-EN"
      },
      {
        "url": "https://multi.govoet.my.id/?ss=hd1",
        "label": "CH-EN"
      },
      {
        "url": "https://multi.govoet.my.id/?ss=hd9",
        "label": "CH-EN"
      },
      {
        "url": "https://multi.govoet.my.id/?ss=sporttv1",
        "label": "CH-PT"
      }
    ],
    "is_womens": false
  },
  {
    "id": "Indonesia-Chinese-Taipei",
    "league": "Friendly International",
    "team1": {
      "name": "Indonesia",
      "logo": "https://static.flashscore.com/res/image/data/WvrcHkXg-QBz8eAFI.png"
    },
    "team2": {
      "name": "Chinese Taipei",
      "logo": "https://static.flashscore.com/res/image/data/xjrSUIEG-251yRjVj.png"
    },
    "kickoff_date": "2025-09-05",
    "kickoff_time": "20:30",
    "match_date": "2025-09-05",
    "match_time": "20:30",
    "duration": "3.5",
    "icon": "https://via.placeholder.com/30.png?text=Soccer",
    "servers": [
      {
        "url": "https://list-govoet.blogspot.com/p/embed1.html",
        "label": "CH-ID"
      },
      {
        "url": "https://list-govoet.blogspot.com/p/embed2.html",
        "label": "CH-ID"
      },
      {
        "url": "https://list-govoet.blogspot.com/p/channel1.html",
        "label": "CH-ID"
      }
    ],
    "is_womens": false
  }
]